{
  "blogs": [
    {
      "title": "My new Website",
      "body": "lorem ipsum..",
      "author": "mario",
      "id": 1
    },
    {
      "title": "Welcome party!",
      "body": "lorem ipsum..",
      "author": "yoshi",
      "id": 2
    },
    {
      "title": "hello",
      "body": "hellovgv",
      "author": "mario",
      "id": 8
    },
    {
      "title": "hello",
      "body": "hellovgv",
      "author": "mario",
      "id": 9
    },
    {
      "title": "hello",
      "body": "hellovgv",
      "author": "mario",
      "id": 11
    },
    {
      "title": "hello",
      "body": "hellovgv",
      "author": "mario",
      "id": 12
    },
    {
      "title": "hello",
      "body": "hellovgv",
      "author": "mario",
      "id": 13
    },
    {
      "title": "hello",
      "body": "hellovgv",
      "author": "mario",
      "id": 14
    },
    {
      "title": "hello",
      "body": "hellovgv",
      "author": "mario",
      "id": 15
    },
    {
      "title": "hello",
      "body": "hellovgv",
      "author": "mario",
      "id": 16
    },
    {
      "title": "hello",
      "body": "hellovgv",
      "author": "mario",
      "id": 17
    },
    {
      "title": "hello",
      "body": "hellovgv",
      "author": "mario",
      "id": 18
    },
    {
      "title": "hello",
      "body": "hellovgv",
      "author": "mario",
      "id": 19
    },
    {
      "title": "hello",
      "body": "hello",
      "author": "mario",
      "id": 20
    },
    {
      "title": "hello",
      "body": "hello",
      "author": "mario",
      "id": 22
    }
  ]
}